g4epy/__init__.py
g4epy/console_run_sink.py
g4epy/g4e.py
g4epy/notebook_run_sink.py
g4epy/runner.py
g4epy/test_env.py
g4epy/version.py
g4epy-0.0.1.dist-info/METADATA
g4epy-0.0.1.dist-info/WHEEL
g4epy-0.0.1.dist-info/top_level.txt
g4epy-0.0.1.dist-info/RECORD
